road_collisions_anz/__init__.py
road_collisions_anz/bin/__init__.py
road_collisions_anz/bin/load.py
road_collisions_anz/models/__init__.py
road_collisions_anz/models/collision.py
road_collisions_anz/resources/anz/anz.csv.tgz
road_collisions_anz-0.0.1.dist-info/METADATA
road_collisions_anz-0.0.1.dist-info/WHEEL
road_collisions_anz-0.0.1.dist-info/entry_points.txt
road_collisions_anz-0.0.1.dist-info/top_level.txt
road_collisions_anz-0.0.1.dist-info/RECORD
