Metadata-Version: 2.1
Name: road-collisions-anz
Version: 0.0.1
Summary: Road collision data for Australia and New Zealand
Home-page: https://github.com/RobertLucey/road-collisions-anz
Author: Robert Lucey
License: UNKNOWN
Platform: UNKNOWN
Requires-Python: >=3.6
Requires-Dist: road-collisions-base
